{
    "data": {
        "__type": {
            "name": "EscalationEdge",
            "description": "An edge in a connection.",
            "fields": [
                {
                    "name": "cursor",
                    "type": {
                        "name": null,
                        "kind": "NON_NULL",
                        "ofType": {
                            "name": "String",
                            "kind": "SCALAR"
                        }
                    }
                },
                {
                    "name": "node",
                    "type": {
                        "name": "Escalation",
                        "kind": "OBJECT",
                        "ofType": null
                    }
                }
            ]
        }
    }
}