{
    "data": {
        "__type": {
            "name": "SwagConnection",
            "description": "The connection type for Swag.",
            "fields": [
                {
                    "name": "edges",
                    "type": {
                        "name": null,
                        "kind": "LIST",
                        "ofType": {
                            "name": "SwagEdge",
                            "kind": "OBJECT"
                        }
                    }
                },
                {
                    "name": "nodes",
                    "type": {
                        "name": null,
                        "kind": "LIST",
                        "ofType": {
                            "name": "Swag",
                            "kind": "OBJECT"
                        }
                    }
                },
                {
                    "name": "pageInfo",
                    "type": {
                        "name": null,
                        "kind": "NON_NULL",
                        "ofType": {
                            "name": "PageInfo",
                            "kind": "OBJECT"
                        }
                    }
                },
                {
                    "name": "total_count",
                    "type": {
                        "name": null,
                        "kind": "NON_NULL",
                        "ofType": {
                            "name": "Int",
                            "kind": "SCALAR"
                        }
                    }
                }
            ]
        }
    }
}