{
    "data": {
        "__type": {
            "name": "WriteUp",
            "description": "A write-up",
            "fields": [
                {
                    "name": "_id",
                    "type": {
                        "name": null,
                        "kind": "NON_NULL",
                        "ofType": {
                            "name": "ID",
                            "kind": "SCALAR"
                        }
                    }
                },
                {
                    "name": "data_overrides",
                    "type": {
                        "name": "Hash",
                        "kind": "SCALAR",
                        "ofType": null
                    }
                },
                {
                    "name": "id",
                    "type": {
                        "name": null,
                        "kind": "NON_NULL",
                        "ofType": {
                            "name": "ID",
                            "kind": "SCALAR"
                        }
                    }
                },
                {
                    "name": "template_config_key",
                    "type": {
                        "name": null,
                        "kind": "NON_NULL",
                        "ofType": {
                            "name": "String",
                            "kind": "SCALAR"
                        }
                    }
                }
            ]
        }
    }
}